{"_id":"63689d5ce80bff5a994f443e","area_name":"Shady Lady","shortCode":"","climbs":[{"_id":"NBFDl2UBVealWMmQ0axOww==","name":"Dirty Hairy","yds":"5.9","grades":{"yds":"5.9","french":"5c"},"fa":"Kevin Nelson & D. Nedever (1981)","type":{"trad":true},"safety":"UNSPECIFIED","metadata":{"lnglat":{"type":"Point","coordinates":[-120.13638,38.79902]},"left_right_index":999999,"mp_id":"117617845","mp_crag_id":"117617768","climb_id":"NBFDl2UBVealWMmQ0axOww==","areaRef":"BceJE2tXXjyuovpld26MDA=="},"content":{"description":"Climb the dirty corner straight up and exit through the flake.  Top Notch finish.\n\nThis route eats up gear, no shortage of places for pro.\n\nAfter this cleans up, it will be the best single pitch 5.9 at imo at the leap.","protection":"full set of nuts, doubles to 2\" and one 3.\n\nGear Anchor to belay.\n\nSlings with one carabiner off to the right at the top. rap off.","location":"At the base of the trail."},"__v":0}],"children":[],"ancestors":"1db1e8ba-a40e-587c-88a4-64f5ea814b8e,1e18b6dd-d8b1-5c36-b555-175190184622,6d6152bc-0bbc-501a-9891-f11b5d49c911,f2c3db33-a8f4-5afc-a1c7-db5c8b227244,b7663f40-eea7-5cad-8055-e8fe3e93288f,05c78913-6b57-5e3c-aea2-fa65776e8c0c","pathTokens":["USA","California","Lake Tahoe","Highway 50 Corridor","Lover's Leap","Shady Lady"],"gradeContext":"US","aggregate":{"byGrade":[{"count":1,"label":"5.9"}],"byDiscipline":{"trad":{"total":1,"bands":{"unknown":0,"beginner":0,"intermediate":1,"advanced":0,"expert":0}}},"byGradeBand":{"unknown":0,"beginner":0,"intermediate":1,"advanced":0,"expert":0}},"metadata":{"isBoulder":false,"isDestination":false,"leaf":true,"lnglat":{"type":"Point","coordinates":[-120.13638,38.79902]},"bbox":[-120.13695696919496,38.79857033981813,-120.13580303080505,38.799469660181856],"left_right_index":-1,"ext_id":"117617768","area_id":"BceJE2tXXjyuovpld26MDA==","polygon":{"type":"Polygon","coordinates":[[[-120.13695696919496,38.79857033981813],[-120.13580303080505,38.79857033981813],[-120.13580303080505,38.799469660181856],[-120.13695696919496,38.799469660181856],[-120.13695696919496,38.79857033981813]]]}},"content":{"description":""},"density":0,"totalClimbs":1,"__v":1,"createdAt":"2022-11-07T05:53:55.116Z","updatedAt":"2024-01-20T00:57:33.499Z"}