{"_id":"6368a36ae80bff5a99582a01","area_name":"Skid Mark Boulder","shortCode":"","climbs":[{"_id":"ZZB+WeKDWmO68gsCjPxpqg==","name":"Skid Mark (Ephemeral Streak)","yds":"V1-2","grades":{"yds":"V1-2","font":"5","vscale":"V1-2"},"fa":"Aaron Vit","type":{"bouldering":true},"safety":"UNSPECIFIED","metadata":{"lnglat":{"type":"Point","coordinates":[-121.84467,45.49717]},"left_right_index":0,"mp_id":"114790442","mp_crag_id":"109252443","climb_id":"ZZB+WeKDWmO68gsCjPxpqg==","areaRef":"wv1fR641UOml8IHz0BP4fQ=="},"content":{"description":"Start with both hands in the hairline crack and work up the \"skid mark\". Interesting movement for a slab climb. Weird landing but not necessarily unsafe. Scoot down the mossy ramp to down climb.","protection":"","location":""},"__v":0}],"children":[],"ancestors":"1db1e8ba-a40e-587c-88a4-64f5ea814b8e,5f05ed84-1a18-52d9-b8cf-77f8fd01e061,f7ecbea8-fb28-52ef-98cc-e0b25b55bee7,86d25bc4-9cf2-59b0-a954-7def48481d7c,0d5495cf-709d-571e-b2aa-3303f000a4c0,c2fd5f47-ae35-50e9-a5f0-81f3d013f87d","pathTokens":["USA","Oregon","Mt. Hood National Forest","Lost Lake Boulders","Extra Crispy Boulders","Skid Mark Boulder"],"gradeContext":"US","aggregate":{"byGrade":[{"count":1,"label":"V1-2"}],"byDiscipline":{"bouldering":{"total":1,"bands":{"unknown":0,"beginner":0,"intermediate":1,"advanced":0,"expert":0}}},"byGradeBand":{"unknown":0,"beginner":0,"intermediate":1,"advanced":0,"expert":0}},"metadata":{"isBoulder":false,"isDestination":false,"leaf":true,"lnglat":{"type":"Point","coordinates":[-121.84467,45.49717]},"bbox":[-121.84531150611981,45.49672033981813,-121.84402849388017,45.49761966018187],"left_right_index":-1,"ext_id":"109252443","area_id":"wv1fR641UOml8IHz0BP4fQ==","polygon":{"type":"Polygon","coordinates":[[[-121.84531150611981,45.49672033981813],[-121.84402849388017,45.49672033981813],[-121.84402849388017,45.49761966018187],[-121.84531150611981,45.49761966018187],[-121.84531150611981,45.49672033981813]]]}},"content":{"description":"Slab Climb. Start in seam and move up edges to the top. V2"},"density":0,"totalClimbs":1,"__v":1,"createdAt":"2022-11-07T06:19:24.875Z","updatedAt":"2024-02-19T18:39:12.306Z"}