{"_id":"63689de0e80bff5a994f9be5","area_name":"Judge Rock","shortCode":"","climbs":[{"_id":"aYDkVE6EXJan2NADwnSOXg==","name":"Innocence","yds":"V3","grades":{"yds":"V3","font":"6A","vscale":"V3"},"fa":"unknown","type":{"bouldering":true},"safety":"UNSPECIFIED","metadata":{"lnglat":{"type":"Point","coordinates":[-108.49787,38.90149]},"left_right_index":0,"mp_id":"108367942","mp_crag_id":"108367938","climb_id":"aYDkVE6EXJan2NADwnSOXg==","areaRef":"MGrPyfoSVhmEBJxa8jQ33g=="},"content":{"description":"Stand start with hands on the sloping crimp rail about six feet off the ground.  From there, work the technical feet, gain the lip, traverse left a few feet, throw a heel over the lip, and top it out up the featured slab.\n\nAdding a sit to the problem will likely add some value, but I couldn't pull off the start holds.","protection":"Bring a few pads, the landing is good, just don't pitch off the top out, as the slope behind is steep and ridden with rocks and trees.","location":"It is located on the west face of Judge Rock."},"__v":0}],"children":[],"ancestors":"1db1e8ba-a40e-587c-88a4-64f5ea814b8e,ab48aed5-2e8d-54bb-b099-6140fe1f098f,e8ca6047-b04f-5bd0-afb7-9b485b643d4f,4246501c-a558-5494-8fdc-ef635bbb8bbb,b9b123a7-fbea-5dff-81ca-bb33975aa143,f4c2e930-325e-56ce-850c-ca86bed85c98,e8ab21f6-7721-50d8-a47b-e73115d43110,306acfc9-fa12-5619-8404-9c5af23437de","pathTokens":["USA","Colorado","Grand Junction Area","Unaweep Canyon","Nine Mile Hill","Nine Mile Bouldering","Black Wave Boulder Area","Judge Rock"],"gradeContext":"US","aggregate":{"byGrade":[{"count":1,"label":"V3"}],"byDiscipline":{"bouldering":{"total":1,"bands":{"unknown":0,"beginner":0,"intermediate":0,"advanced":1,"expert":0}}},"byGradeBand":{"unknown":0,"beginner":0,"intermediate":0,"advanced":1,"expert":0}},"metadata":{"isBoulder":false,"isDestination":false,"leaf":true,"lnglat":{"type":"Point","coordinates":[-108.49787,38.90149]},"bbox":[-108.49844780093355,38.901040339818145,-108.49729219906644,38.90193966018187],"left_right_index":-1,"ext_id":"108367938","area_id":"MGrPyfoSVhmEBJxa8jQ33g==","polygon":{"type":"Polygon","coordinates":[[[-108.49844780093355,38.901040339818145],[-108.49729219906644,38.901040339818145],[-108.49729219906644,38.90193966018187],[-108.49844780093355,38.90193966018187],[-108.49844780093355,38.901040339818145]]]}},"content":{"description":""},"density":0,"totalClimbs":1,"__v":1,"createdAt":"2022-11-07T05:56:33.111Z","updatedAt":"2024-01-20T01:00:41.359Z"}