{"_id":"6368a44ee80bff5a9959c1ba","area_name":"Baluster, The","shortCode":"","climbs":[{"_id":"CBzEoA6pWt6Kn5WjnF6PuA==","name":"Mary Poppins Delight","yds":"5.9","grades":{"yds":"5.9","french":"5c"},"fa":"Chris Hirsch & Cheryl Mayer, summer 2019 (ground-up)","type":{"trad":true},"safety":"UNSPECIFIED","metadata":{"lnglat":{"type":"Point","coordinates":[-103.5317,43.85074]},"left_right_index":0,"mp_id":"118015571","mp_crag_id":"117663445","climb_id":"CBzEoA6pWt6Kn5WjnF6PuA==","areaRef":"NIgK5r9kVIifMH5BC5tp6g=="},"content":{"description":"Currently the only route on this small spire. Start by stemming next to thin seam for the first 25'. Then follow finger crack that protects very well. As crack dies, work out to arete, clip a bolt and pull over into trough. Easy face climbing to summit. Sling the long oblong summit for anchor. Needles style rappel.","protection":"1 bolt, single rack; micro-medium","location":"Climbs the thin seam just right of North corner. At entrance of narrow corridor."},"__v":0}],"children":[],"ancestors":"1db1e8ba-a40e-587c-88a4-64f5ea814b8e,253ab2e3-944f-5c5f-8477-58a428c86291,eb71723c-d454-5686-9f66-8bbd19c7143e,afb36576-ca26-503f-97d5-8ed0f57fb151,34880ae6-bf64-5488-9f30-7e410b9b69ea","pathTokens":["USA","South Dakota","Custer State Park","Picket Fence","Baluster, The"],"gradeContext":"US","aggregate":{"byGrade":[{"count":1,"label":"5.9"}],"byDiscipline":{"trad":{"total":1,"bands":{"unknown":0,"beginner":0,"intermediate":1,"advanced":0,"expert":0}}},"byGradeBand":{"unknown":0,"beginner":0,"intermediate":1,"advanced":0,"expert":0}},"metadata":{"isBoulder":false,"isDestination":false,"leaf":true,"lnglat":{"type":"Point","coordinates":[-103.5317,43.85074]},"bbox":[-103.53232353470757,43.85029033981815,-103.53107646529244,43.851189660181866],"left_right_index":-1,"ext_id":"117663445","area_id":"NIgK5r9kVIifMH5BC5tp6g=="},"content":{"description":"Nestled up against Tricky Picket's NE corner is this smaller, hidden spire. Has narrow corridors on it's West and North sides.  \n\n  At first I thought this may be the Conns' 'Picket Sign' spire, but it doesn't quite match the description. And the easiest looking route up this has very suspect rock (i backed off). So this may be a new summit in the Picket Fence!? Correct me if I'm wrong."},"density":0,"totalClimbs":1,"__v":1,"createdAt":"2022-11-07T06:23:17.110Z","updatedAt":"2024-01-15T16:48:33.597Z"}