{"_id":"6368a821609a28119996c1b5","area_name":"United Arab Emirates","shortCode":"ARE","climbs":[],"children":[],"ancestors":"2e2b4193-fbd7-5252-b407-f6a49712f8cf","pathTokens":["United Arab Emirates"],"gradeContext":"US","aggregate":{"byGrade":[],"byGradeBand":{"unknown":0,"beginner":0,"intermediate":0,"advanced":0,"expert":0}},"metadata":{"isBoulder":false,"isDestination":false,"leaf":false,"lnglat":{"type":"Point","coordinates":[54,24]},"bbox":[53.999507785651936,23.99955033981814,54.00049221434806,24.00044966018186],"left_right_index":-1,"ext_id":"","area_id":"LitBk/vXUlK0B/aklxL4zw==","polygon":{"type":"Polygon","coordinates":[[[53.999507785651936,23.99955033981814],[54.00049221434806,23.99955033981814],[54.00049221434806,24.00044966018186],[53.999507785651936,24.00044966018186],[53.999507785651936,23.99955033981814]]]}},"content":{"description":""},"density":0,"totalClimbs":0,"__v":1,"createdAt":"2022-11-07T06:39:30.027Z","updatedAt":"2024-02-19T18:48:13.383Z"}