{"_id":"63689d5ce80bff5a994f4fc1","area_name":"Whizz Domes","shortCode":"","climbs":[],"children":["63689d5ce80bff5a994f4fc2","63689d5ce80bff5a994f4fc3"],"ancestors":"1db1e8ba-a40e-587c-88a4-64f5ea814b8e,1e18b6dd-d8b1-5c36-b555-175190184622,8ab53875-745f-5076-b396-d3d84945e52c,ce6ec458-d8d0-5439-aa24-025a8a8ec2e4,5abff9b7-73d0-5461-9603-7b78a1d00100","pathTokens":["USA","California","Yosemite National Park","Tuolumne Meadows","Whizz Domes"],"gradeContext":"US","aggregate":{"byGrade":[{"count":1,"label":"5.12c"},{"count":1,"label":"5.13b"},{"count":2,"label":"5.12a"},{"count":1,"label":"5.12b"},{"count":1,"label":"5.11b"},{"count":1,"label":"5.11a"}],"byDiscipline":{"trad":{"total":3,"bands":{"unknown":0,"beginner":0,"intermediate":0,"advanced":3,"expert":0}},"sport":{"total":4,"bands":{"unknown":0,"beginner":0,"intermediate":0,"advanced":3,"expert":1}},"aid":{"total":1,"bands":{"unknown":1,"beginner":0,"intermediate":0,"advanced":0,"expert":0}},"tr":{"total":2,"bands":{"unknown":0,"beginner":0,"intermediate":0,"advanced":1,"expert":1}}},"byGradeBand":{"unknown":0,"beginner":0,"intermediate":0,"advanced":6,"expert":1}},"metadata":{"isBoulder":false,"isDestination":false,"leaf":false,"lnglat":{"type":"Point","coordinates":[-119.440055,37.87091]},"bbox":[-119.44076963537631,37.86921033981814,-119.43934038395223,37.872609660181865],"left_right_index":-1,"ext_id":"","area_id":"Wr/5t3PQVGGWA3t4odABAA==","polygon":{"type":"Polygon","coordinates":[[[-119.44047961604778,37.86921033981814],[-119.44076963537631,37.871710339818144],[-119.44076963537631,37.872609660181865],[-119.43963036462368,37.872609660181865],[-119.43934038395223,37.87010966018187],[-119.43934038395223,37.86921033981814],[-119.44047961604778,37.86921033981814]]]}},"content":{"description":""},"density":1.4,"totalClimbs":7,"__v":1,"createdAt":"2022-11-07T05:54:34.524Z","updatedAt":"2024-01-20T01:11:07.105Z"}