{"_id":"63689d5ce80bff5a994f5379","area_name":"Turtleback Dome","shortCode":"","climbs":[],"children":[],"ancestors":"1db1e8ba-a40e-587c-88a4-64f5ea814b8e,1e18b6dd-d8b1-5c36-b555-175190184622,8ab53875-745f-5076-b396-d3d84945e52c,0f1eddf1-5a79-556e-92f6-0d91627e1f2f,662fc058-2269-5b7a-b715-71dcd4f34c93,7f163294-2d58-5a46-9dd0-e37e7a1e91f6","pathTokens":["USA","California","Yosemite National Park","Yosemite Valley","* Yosemite Valley Bouldering","Turtleback Dome"],"gradeContext":"US","aggregate":{"byGrade":[],"byGradeBand":{"unknown":0,"beginner":0,"intermediate":0,"advanced":0,"expert":0}},"metadata":{"isBoulder":false,"isDestination":false,"leaf":true,"lnglat":{"type":"Point","coordinates":[-119.7062,37.7133]},"bbox":[-119.70676841191273,37.71285033981814,-119.70563158808726,37.71374966018187],"left_right_index":-1,"ext_id":"108023884","area_id":"fxYylC1YWkad0ON+eh6R9g=="},"content":{"description":""},"density":0,"totalClimbs":0,"__v":1,"createdAt":"2022-11-07T05:54:47.052Z","updatedAt":"2022-11-25T11:14:43.657Z"}