{"_id":"6368a29ce80bff5a9956b0fe","area_name":"Diente","shortCode":"","climbs":[{"_id":"j7dmhhHNWTu1hcuKgMyR+g==","name":"Tooth-ache","yds":"V3","grades":{"yds":"V3","font":"6A","vscale":"V3"},"fa":"unknown","type":{"bouldering":true},"safety":"UNSPECIFIED","metadata":{"lnglat":{"type":"Point","coordinates":[-82.7904,35.30578]},"left_right_index":2,"mp_id":"108274922","mp_crag_id":"108274897","climb_id":"j7dmhhHNWTu1hcuKgMyR+g==","areaRef":"d77YC6+8UDqZ63JVtqf4SQ=="},"content":{"description":"Match on the good rail then throw a delicate heel to get you to the next holds. Keep good body tension and try to get the top out jug up and left.","protection":"pad. Good landing but watch the try.","location":"Problem that faces the trail."},"__v":0},{"_id":"KAm3dL14VNSG6gRbVV7X8A==","name":"Route Canal","yds":"V5","grades":{"yds":"V5","font":"6C","vscale":"V5"},"fa":"unknown","type":{"bouldering":true},"safety":"UNSPECIFIED","metadata":{"lnglat":{"type":"Point","coordinates":[-82.7904,35.30578]},"left_right_index":1,"mp_id":"108274944","mp_crag_id":"108274897","climb_id":"KAm3dL14VNSG6gRbVV7X8A==","areaRef":"d77YC6+8UDqZ63JVtqf4SQ=="},"content":{"description":"Presumably start on two crimps on the closest rail to the arete with feet on tenuous holds directly below and on the big ledge around the front.","protection":"pad","location":"located on blunt arete"},"__v":0},{"_id":"M5ELdJ0NWyaJKHeNhBdn+g==","name":"Artificial Bridge","yds":"V5","grades":{"yds":"V5","font":"6C","vscale":"V5"},"fa":"unknown","type":{"bouldering":true},"safety":"UNSPECIFIED","metadata":{"lnglat":{"type":"Point","coordinates":[-82.7904,35.30578]},"left_right_index":0,"mp_id":"108274967","mp_crag_id":"108274897","climb_id":"M5ELdJ0NWyaJKHeNhBdn+g==","areaRef":"d77YC6+8UDqZ63JVtqf4SQ=="},"content":{"description":"The rating is a total guess. I worked it like 5 minutes but seems like some tricky balance would get it.","protection":"pad","location":"Far left corner of the boulder"},"__v":0}],"children":[],"ancestors":"1db1e8ba-a40e-587c-88a4-64f5ea814b8e,b51eaea8-8aee-5fa5-b892-180460bb414d,09830eb9-3d49-51e3-8127-6506b4f459de,93c393dc-b302-5b9f-b506-bc3aeb93f430,ff6385fc-ad64-5c7a-9a25-f2c6a858fb5c,c79fd3c7-2c8e-5011-a47c-ec80f512250e,77bed80b-afbc-503a-99eb-7255b6a7f849","pathTokens":["USA","North Carolina","1. Southern Mountains Region","Looking Glass Rock","Looking Glass Boulders","Northside Boulders","Diente"],"gradeContext":"US","aggregate":{"byGrade":[{"count":1,"label":"V3"},{"count":2,"label":"V5"}],"byDiscipline":{"bouldering":{"total":3,"bands":{"unknown":0,"beginner":0,"intermediate":0,"advanced":3,"expert":0}}},"byGradeBand":{"unknown":0,"beginner":0,"intermediate":0,"advanced":3,"expert":0}},"metadata":{"isBoulder":false,"isDestination":false,"leaf":true,"lnglat":{"type":"Point","coordinates":[-82.7904,35.30578]},"bbox":[-82.79095100060309,35.305330339818134,-82.7898489993969,35.30622966018186],"left_right_index":-1,"ext_id":"108274897","area_id":"d77YC6+8UDqZ63JVtqf4SQ=="},"content":{"description":""},"density":0,"totalClimbs":3,"__v":1,"createdAt":"2022-11-07T06:16:01.410Z","updatedAt":"2024-01-15T16:47:42.820Z"}