{"_id":"64143045f0cf00832960d459","area_name":"Mount Zacky","shortCode":"","climbs":[{"_id":"NDOn9kRDSImYkzIp6uv+3g==","name":"Beach Vacation","grades":{"yds":"5.10-"},"type":{"trad":true,"sport":false,"bouldering":false,"alpine":true,"snow":false,"ice":false,"mixed":false,"aid":false,"tr":false},"gradeContext":"US","fa":"\"Thor Stewart & Zack Goldberg-Poch, July 2019\"","length":606,"content":{"description":"This route stays on the best rock of the wall and meanders up a slabby face to the looming head-wall cracks.\nThe jewel of this route is the top 4 pitches of splitter hand cracks on great rock.\n\nDescent: Rappel the route.\n\nOn the south shoulder of Midgard, between Asgard and Freya. \nDouble 60m ropes, double rack to 3\", one 4\" &amp; 5\""},"metadata":{"left_right_index":-1,"areaRef":"yFtJF2BMUt2JBOiX/khnhQ==","lnglat":{"type":"Point","coordinates":[-65.27731,66.6537]}},"createdBy":"iWAKJJDWXzGSKVgKaOyWxg==","_change":{"user":"iWAKJJDWXzGSKVgKaOyWxg==","historyId":"64143047f0cf00832960d467","operation":"updateClimb","seq":0},"updatedAt":"2023-03-17T09:17:59.275Z"}],"children":[],"ancestors":"2996145f-e1ba-5b56-9da8-30c64ccc3776,6f233d1b-859a-5bfe-b1ca-246a5dbf326e,e112e034-8925-5e3b-8f07-5f883301fd35,f35ea58f-3364-58c9-a229-db634a30fdc6,c85b4917-604c-52dd-8904-e897fe486785","pathTokens":["Canada","Nunavut","Baffin Island","Baffin Mountains","Mount Zacky"],"gradeContext":"US","aggregate":{"byGrade":[{"count":1,"label":"5.10-"}],"byDiscipline":{"trad":{"total":1,"bands":{"unknown":0,"beginner":0,"intermediate":1,"advanced":0,"expert":0}},"alpine":{"total":1,"bands":{"unknown":0,"beginner":0,"intermediate":1,"advanced":0,"expert":0}}},"byGradeBand":{"unknown":0,"beginner":0,"intermediate":1,"advanced":0,"expert":0}},"metadata":{"isDestination":false,"leaf":true,"isBoulder":false,"lnglat":{"type":"Point","coordinates":[-65.27731,66.6537]},"bbox":[-65.27844468155223,66.65325033981813,-65.27617531844776,66.65414966018186],"left_right_index":-1,"ext_id":"","area_id":"yFtJF2BMUt2JBOiX/khnhQ=="},"content":{"description":"Mt Zacky is a sub-summit, of a sub-summit of Mt. Midgard.  \n If you tire of glacier travel to Asgard and surrounding worthy objectives, this wall is a great spot for \"cragging\"; but its still more than 700m tall."},"density":0,"totalClimbs":0,"_change":{"user":"rxDUVMc5QUiq75Hpq+nDVw==","historyId":"64143047f0cf00832960d467","prevHistoryId":"64143046f0cf00832960d461","operation":"updateClimb","seq":0},"createdBy":"rxDUVMc5QUiq75Hpq+nDVw==","__v":2,"createdAt":"2023-03-17T09:17:57.284Z","updatedAt":"2024-01-15T16:52:26.153Z","updatedBy":"iWAKJJDWXzGSKVgKaOyWxg=="}