{"_id":"6368a57ce80bff5a995b83fd","area_name":"A.P.D. Boulder","shortCode":"","climbs":[{"_id":"cAY50t1HWt6NtetQsWnR9Q==","name":"Back At The Funny Farm","yds":"V0","grades":{"yds":"V0","font":"4","vscale":"V0"},"fa":"unknown","type":{"bouldering":true},"safety":"UNSPECIFIED","metadata":{"lnglat":{"type":"Point","coordinates":[-72.89825,44.42943]},"left_right_index":1,"mp_id":"108326764","mp_crag_id":"108326758","climb_id":"cAY50t1HWt6NtetQsWnR9Q==","areaRef":"B23wrZI/Xr64Oh7WdxVB4w=="},"content":{"description":"Sit start on the right end of the rail, with right hand in a pocket.  Climb the rail left to the high point.","protection":"2 pads.  One for all the pointy rocks on the ground, and one for the boulder at your back, in case a foothold breaks.","location":"Right rail of the overhanging west face."},"__v":0},{"_id":"ZxKpU/5WWT6Op0XOM1s+Dw==","name":"Another Perfect Day","yds":"V0","grades":{"yds":"V0","font":"4","vscale":"V0"},"fa":"unknown","type":{"bouldering":true},"safety":"UNSPECIFIED","metadata":{"lnglat":{"type":"Point","coordinates":[-72.89825,44.42943]},"left_right_index":0,"mp_id":"108326771","mp_crag_id":"108326758","climb_id":"ZxKpU/5WWT6Op0XOM1s+Dw==","areaRef":"B23wrZI/Xr64Oh7WdxVB4w=="},"content":{"description":"Sit directly underneath the high point of the boulder.  Right hand on a low, suspect knob and left hand on an undercling.  Head left towards a huge jug, then to a quartz jug, then another jug near the high point then a top out jug.  It's like being in a gym.","protection":"Two pads.  Watch out for crumbly feet.","location":"Directly underneath the high point of the  overhanging west face of the boulder."},"__v":0}],"children":[],"ancestors":"1db1e8ba-a40e-587c-88a4-64f5ea814b8e,f0144402-e84e-5e32-88ee-648033ed0e77,c39deb6c-8546-520a-9c31-aee4f0c33a5c,f90b510e-efcb-57b2-aad8-114f0cd564c0,9e5abc93-ea8f-50c8-b864-8fc04586c3cb,53dd018e-5a3b-5c2e-8ee2-21b21b7fa724,6d778549-6a21-584c-98e2-b40436d4971c,076df0ad-923f-5ebe-b83a-1ed6771541e3","pathTokens":["USA","Vermont","1. Northern Vermont","Bolton Area","Upper Upper West","Upper Upper West Boulders","Second Set","A.P.D. Boulder"],"gradeContext":"US","aggregate":{"byGrade":[{"count":2,"label":"V0"}],"byDiscipline":{"bouldering":{"total":2,"bands":{"unknown":0,"beginner":2,"intermediate":0,"advanced":0,"expert":0}}},"byGradeBand":{"unknown":0,"beginner":2,"intermediate":0,"advanced":0,"expert":0}},"metadata":{"isBoulder":false,"isDestination":false,"leaf":true,"lnglat":{"type":"Point","coordinates":[-72.89825,44.42943]},"bbox":[-72.89887967633133,44.42898033981814,-72.89762032366866,44.429879660181854],"left_right_index":-1,"ext_id":"108326758","area_id":"B23wrZI/Xr64Oh7WdxVB4w=="},"content":{"description":"A good warm up boulder, but some of the footholds are still a bit questionable."},"density":0,"totalClimbs":2,"__v":1,"createdAt":"2022-11-07T06:28:16.804Z","updatedAt":"2024-01-15T16:49:55.230Z"}