{"_id":"63689d5ce80bff5a994f5376","area_name":"* Yosemite Valley Bouldering","shortCode":"","climbs":[],"children":["63689d5ce80bff5a994f5377","63689d5ce80bff5a994f5378","63689d5ce80bff5a994f5379","63689d5ce80bff5a994f537a","63689d5ce80bff5a994f537b","63689d5ce80bff5a994f5382","63689d5ce80bff5a994f5385","63689d5ce80bff5a994f5394","63689d5ce80bff5a994f5399","63689d5ce80bff5a994f53a0","63689d5ce80bff5a994f53a2","63689d5ce80bff5a994f53a4","63689d5ce80bff5a994f53a6","63689d5ce80bff5a994f53a9","63689d5ce80bff5a994f53ab","63689d5ce80bff5a994f53af","63689d5ce80bff5a994f53b2","63689d5ce80bff5a994f53d8","63689d5ce80bff5a994f53dd","63689d5ce80bff5a994f5465","63689d5ce80bff5a994f5467","63689d5ce80bff5a994f546a","63689d5ce80bff5a994f546e","63689d5ce80bff5a994f5470","63689d5ce80bff5a994f5474","63689d5ce80bff5a994f5476","63689d5ce80bff5a994f5479"],"ancestors":"1db1e8ba-a40e-587c-88a4-64f5ea814b8e,1e18b6dd-d8b1-5c36-b555-175190184622,8ab53875-745f-5076-b396-d3d84945e52c,0f1eddf1-5a79-556e-92f6-0d91627e1f2f,662fc058-2269-5b7a-b715-71dcd4f34c93","pathTokens":["USA","California","Yosemite National Park","Yosemite Valley","* Yosemite Valley Bouldering"],"gradeContext":"US","aggregate":{"byGrade":[{"count":4,"label":"V12"},{"count":2,"label":"V11"},{"count":12,"label":"V9"},{"count":20,"label":"V6"},{"count":34,"label":"V4"},{"count":19,"label":"V1"},{"count":41,"label":"V0"},{"count":20,"label":"V-easy"},{"count":3,"label":"V3+"},{"count":8,"label":"V0+"},{"count":14,"label":"V7"},{"count":38,"label":"V3"},{"count":15,"label":"V2"},{"count":1,"label":"5.7"},{"count":14,"label":"V8"},{"count":21,"label":"V0-"},{"count":24,"label":"V5"},{"count":5,"label":"V10"},{"count":3,"label":"V6-"},{"count":3,"label":"V4-5"},{"count":1,"label":"V10-"},{"count":1,"label":"V3-"},{"count":3,"label":"V1+"},{"count":2,"label":"V7-"},{"count":2,"label":"V5-6"},{"count":1,"label":"V6-7"},{"count":1,"label":"V4+"},{"count":1,"label":"V5-"},{"count":1,"label":"5.10-"},{"count":1,"label":"V2-"},{"count":1,"label":"V7-8"},{"count":1,"label":"V4-"},{"count":1,"label":"V1-"},{"count":1,"label":"5.10b"},{"count":1,"label":"V8-"},{"count":1,"label":"5.11b"},{"count":1,"label":"5.12b"}],"byDiscipline":{"trad":{"total":2,"bands":{"unknown":0,"beginner":0,"intermediate":2,"advanced":0,"expert":0}},"boulder":{"total":320,"bands":{"unknown":20,"beginner":71,"intermediate":40,"advanced":112,"expert":77}},"tr":{"total":3,"bands":{"unknown":0,"beginner":1,"intermediate":0,"advanced":2,"expert":0}}},"byGradeBand":{"unknown":20,"beginner":72,"intermediate":41,"advanced":112,"expert":77}},"metadata":{"isBoulder":false,"isDestination":false,"leaf":false,"lnglat":{"type":"Point","coordinates":[-119.60190475017636,37.71853192993827]},"bbox":[-119.71632847191343,35.546960339818135,-116.22488734391885,37.751439660181866],"left_right_index":-1,"ext_id":"","area_id":"Zi/AWCJpW3q3FXHc1PNMkw=="},"content":{"description":""},"density":0.0042081370780677205,"totalClimbs":322,"__v":1,"createdAt":"2022-11-07T05:54:47.051Z","updatedAt":"2022-11-25T11:26:06.840Z"}