{"_id":"63689d5ce80bff5a994f4f0b","area_name":"Wasted Boulder","shortCode":"","climbs":[{"_id":"ECo64o/mUKOG3jZ+zWuIjw==","name":"Sasquatch Gets Wasted","yds":"V7","grades":{"yds":"V7","font":"7A+","vscale":"V7"},"fa":"unknown","type":{"bouldering":true},"safety":"UNSPECIFIED","metadata":{"lnglat":{"type":"Point","coordinates":[-119.09438,37.7665]},"left_right_index":0,"mp_id":"110564038","mp_crag_id":"110563757","climb_id":"ECo64o/mUKOG3jZ+zWuIjw==","areaRef":"Km7j4lL/XiGWiH/get+o+w=="},"content":{"description":"Difficult to start and fun to finish.\n\nSit start with right hand on the right side of the arete on a small sharp vertical edge.   Left hand on what ever works.   Make a hard pull up left to the good crimp and then finish it off with engaging moves.","protection":"Pads","location":"Right arete of north face"},"__v":0},{"_id":"pp+1XLZ4WpSd0pjd5iv9xw==","name":"Problem B","yds":"V1","grades":{"yds":"V1","font":"5","vscale":"V1"},"fa":"unknown","type":{"bouldering":true},"safety":"UNSPECIFIED","metadata":{"lnglat":{"type":"Point","coordinates":[-119.09438,37.7665]},"left_right_index":2,"mp_id":"110563860","mp_crag_id":"110563757","climb_id":"pp+1XLZ4WpSd0pjd5iv9xw==","areaRef":"Km7j4lL/XiGWiH/get+o+w=="},"content":{"description":"Start with hands on a good high hold and continue more or less directly up the arete on good but spaced holds.","protection":"Pads and spotters","location":"South west arete"},"__v":0},{"_id":"MofnMxO6Vy++UL1cBB7nQg==","name":"Problem A","yds":"V3","grades":{"yds":"V3","font":"6A","vscale":"V3"},"fa":"unknown","type":{"bouldering":true},"safety":"UNSPECIFIED","metadata":{"lnglat":{"type":"Point","coordinates":[-119.09438,37.7665]},"left_right_index":1,"mp_id":"110563867","mp_crag_id":"110563757","climb_id":"MofnMxO6Vy++UL1cBB7nQg==","areaRef":"Km7j4lL/XiGWiH/get+o+w=="},"content":{"description":"Start with hands on a good input hold about 5 feet up.   Climb the face more or less direct with engaging balancy moves to a delicate finish.","protection":"Pads and spotters","location":"middle of the west face"},"__v":0},{"_id":"ZdwuqPBmWnCcFIopCnsKBQ==","name":"Mara's Problem","yds":"V4","grades":{"yds":"V4","font":"6B","vscale":"V4"},"fa":"unknown","type":{"bouldering":true},"safety":"UNSPECIFIED","metadata":{"lnglat":{"type":"Point","coordinates":[-119.09438,37.7665]},"left_right_index":3,"mp_id":"110564030","mp_crag_id":"110563757","climb_id":"ZdwuqPBmWnCcFIopCnsKBQ==","areaRef":"Km7j4lL/XiGWiH/get+o+w=="},"content":{"description":"Short sharp and crimpy.  Start with right hand on a side-pull and left on a small spike.   Get established on the wall and move up and right to the crux move going for the lip.","protection":"Pads","location":"right side of south face"},"__v":0}],"children":[],"ancestors":"1db1e8ba-a40e-587c-88a4-64f5ea814b8e,1e18b6dd-d8b1-5c36-b555-175190184622,28ecf9b8-3e02-54f1-9a23-26c5d4120483,2d851305-4237-55da-9626-16bb345bb0ad,f93002d8-f872-5865-8cea-8b03e9dd2caa,2151b11a-9def-5728-9883-e05c7b132fce,2a6ee3e2-52ff-5e21-9688-7fe07adfa8fb","pathTokens":["USA","California","Sierra Eastside","June Lake Area","* June Lake Bouldering","Sasquatch Patch","Wasted Boulder"],"gradeContext":"US","aggregate":{"byGrade":[{"count":1,"label":"V7"},{"count":1,"label":"V1"},{"count":1,"label":"V3"},{"count":1,"label":"V4"}],"byDiscipline":{"bouldering":{"total":4,"bands":{"unknown":0,"beginner":0,"intermediate":1,"advanced":2,"expert":1}}},"byGradeBand":{"unknown":0,"beginner":0,"intermediate":1,"advanced":2,"expert":1}},"metadata":{"isBoulder":false,"isDestination":false,"leaf":true,"lnglat":{"type":"Point","coordinates":[-119.09438,37.7665]},"bbox":[-119.09494882056104,37.76605033981814,-119.09381117943897,37.76694966018186],"left_right_index":-1,"ext_id":"110563757","area_id":"Km7j4lL/XiGWiH/get+o+w==","polygon":{"type":"Polygon","coordinates":[[[-119.09494882056104,37.76605033981814],[-119.09381117943897,37.76605033981814],[-119.09381117943897,37.76694966018186],[-119.09494882056104,37.76694966018186],[-119.09494882056104,37.76605033981814]]]}},"content":{"description":""},"density":0,"totalClimbs":4,"__v":1,"createdAt":"2022-11-07T05:54:32.391Z","updatedAt":"2024-02-19T18:29:38.637Z"}