{"_id":"64148f2f135731b69110a7ad","area_name":"School","shortCode":"","climbs":[],"children":[],"ancestors":"2996145f-e1ba-5b56-9da8-30c64ccc3776,2dde9bf9-577b-5f7f-ad93-79babfc891a6,f38818ea-5357-5fab-bf11-a7e7ac80fed7,5e0f51d5-b4ea-5375-875f-1ed3ef3559b9,db041e9f-2993-5f05-8353-93a645a07ac1,22265c48-66f7-509f-b688-e94a02354ee7","pathTokens":["Canada","Quebec","Quebec Ice, Mixed & Alpine","Portneuf","St-Alban Ice & Mixed","School"],"gradeContext":"US","aggregate":{"byGrade":[],"byGradeBand":{"unknown":0,"beginner":0,"intermediate":0,"advanced":0,"expert":0}},"metadata":{"isDestination":false,"leaf":false,"isBoulder":false,"lnglat":{"type":"Point","coordinates":[-72.08024,46.70919]},"bbox":[-180,-90,180,90],"left_right_index":-1,"ext_id":"","area_id":"IiZcSGb3UJ+2iOlKAjVO5w=="},"content":{"description":"L'Amphithéatre du nouveau délire \n School \n Central \n La Guignolée \n Entrance Area"},"density":0,"totalClimbs":0,"_change":{"user":"LVk4CyGzVUKlccwQYeAuDA==","historyId":"64148f30135731b69110a7b5","prevHistoryId":"64148f2f135731b69110a7aa","operation":"updateArea","seq":0},"createdBy":"rxDUVMc5QUiq75Hpq+nDVw==","__v":0,"createdAt":"2023-03-17T16:02:55.037Z","updatedAt":"2023-03-17T16:02:56.231Z","updatedBy":"LVk4CyGzVUKlccwQYeAuDA=="}