{"_id":"64133a1ff0cf0083295d2d82","area_name":"The Back of The Lake","shortCode":"","climbs":[],"children":["64133a21f0cf0083295d2d93","64133a2cf0cf0083295d2e39","64133a36f0cf0083295d2ec7","64133a45f0cf0083295d2f8e","64133a74f0cf0083295d3121","64133d0df0cf0083295d3718","64133d16f0cf0083295d3779","64133d1ef0cf0083295d37e4","64133d27f0cf0083295d3827","64133d3ef0cf0083295d396a","64133d46f0cf0083295d3985"],"ancestors":"2996145f-e1ba-5b56-9da8-30c64ccc3776,27373ec5-14b1-5c42-8f51-8b5fac0a1035,799c5c9a-7c10-5124-bd2e-83ea47291e11,fa6ebe07-759f-5a35-b715-c39bbb8424d2,eb139b12-1171-5604-8ec5-e36f561c4c00","pathTokens":["Canada","Alberta","Banff National Park","Lake Louise","The Back of The Lake"],"gradeContext":"US","aggregate":{"byGrade":[],"byGradeBand":{"unknown":0,"beginner":0,"intermediate":0,"advanced":0,"expert":0}},"metadata":{"isDestination":false,"leaf":false,"isBoulder":false,"lnglat":{"type":"Point","coordinates":[-116.2405,51.4078]},"bbox":[-180,-90,180,90],"left_right_index":-1,"ext_id":"","area_id":"6xObEhFxVgSOxeNvVhxMAA=="},"content":{"description":"The gem of the area.    From a distance the quartzite buttresses tend to get lost within the grandure of the surroundings, however don't let that fool you.   Take the time to wander the trail along the shores of Lake Louise and you will be met with exceptionally good climbing, and more often than not friendly locals willing to show you some of the classics. \n  \n The climbs are generally vertical to gently overhanging and there is a good mixture of sport and trad routes so all comers should be happy. \n  \n Many of the routes are climbable in the summer even when there is a light rain, however, depending on the amount of chalk some do feel a little slimy.\n\nThe gem of the area.    From a distance the quartzite buttresses tend to get lost within the grandure of the surroundings, however don't let that fool you.   Take the time to wander the trail along the shores of Lake Louise and you will be met with exceptionally good climbing, and more often than not friendly locals willing to show you some of the classics. \n  \n The climbs are generally vertical to gently overhanging and there is a good mixture of sport and trad routes so all comers should be happy. \n  \n Many of the routes are climbable in the summer even when there is a light rain, however, depending on the amount of chalk some do feel a little slimy."},"density":0,"totalClimbs":0,"_change":{"user":"rxDUVMc5QUiq75Hpq+nDVw==","historyId":"64133d46f0cf0083295d3982","prevHistoryId":"64133d3ef0cf0083295d3967","operation":"addArea","seq":0},"createdBy":"rxDUVMc5QUiq75Hpq+nDVw==","__v":11,"createdAt":"2023-03-16T15:47:43.053Z","updatedAt":"2023-03-16T15:59:59.688Z","updatedBy":"rxDUVMc5QUiq75Hpq+nDVw=="}