{"_id":"64142105f0cf008329602e55","area_name":"Upper Deck","shortCode":"","climbs":[{"_id":"09IIuBqcS5uKVEJ97qWO6g==","name":"Dirty Dangles","grades":{"yds":"5.8"},"type":{"trad":true,"sport":false,"bouldering":false,"alpine":false,"snow":false,"ice":false,"mixed":false,"aid":false,"tr":false},"gradeContext":"US","fa":"A. Klop","length":8,"content":{"description":"\nTo the right of the main wall and to the right of the large dead tree leaning against the wall. Starts with some tricky pro then as the crack widens the protection improves. \n\n\n\nStart beside the leaning tree.\n\nStandard rack with nuts."},"metadata":{"left_right_index":-1,"areaRef":"u3L8NDluU+CiG52/PVsOwQ==","lnglat":{"type":"Point","coordinates":[-125.08109,49.6225]}},"createdBy":"M22iU8lNXFqdd6EWB6Eudw==","_change":{"user":"M22iU8lNXFqdd6EWB6Eudw==","historyId":"64142107f0cf008329602e66","operation":"updateClimb","seq":0},"updatedAt":"2023-03-17T08:12:55.639Z"},{"_id":"Y8dWv9VPSAu49po3YxT1pA==","name":"Dr. Google Knows Best","grades":{"yds":"5.8"},"type":{"trad":false,"sport":true,"bouldering":false,"alpine":false,"snow":false,"ice":false,"mixed":false,"aid":false,"tr":false},"gradeContext":"US","fa":"A. Klop","length":8,"content":{"description":"\nStart up higher to the right. Climb starts with an awkward mantle move to the first bolt. Head up the ramp to the right and use an undercling to get up to the third bolt. The crux comes after the second ledge as you pull up through the crack system. \n\n\n\nLine on the right up the crack system.\n\n8 bolts"},"metadata":{"left_right_index":-1,"areaRef":"u3L8NDluU+CiG52/PVsOwQ==","lnglat":{"type":"Point","coordinates":[-125.08109,49.6225]}},"createdBy":"M22iU8lNXFqdd6EWB6Eudw==","_change":{"user":"M22iU8lNXFqdd6EWB6Eudw==","historyId":"64142108f0cf008329602e70","operation":"updateClimb","seq":0},"updatedAt":"2023-03-17T08:12:56.104Z"},{"_id":"/TstW6U8SmKbEzkotgEpFQ==","name":"Fuzzy Little Man Peach","grades":{"yds":"5.9"},"type":{"trad":false,"sport":true,"bouldering":false,"alpine":false,"snow":false,"ice":false,"mixed":false,"aid":false,"tr":false},"gradeContext":"US","fa":"A. Klop","length":8,"content":{"description":"\nStart up the ramp and clip the shared first bolt of 'greheheasy', Stay left up the dihedral and crimp your way to the ledge and a juggy finish. \n\n\n\nMain wall at upper deck. Left line beside the leaning tree. \n\n7 bolts"},"metadata":{"left_right_index":-1,"areaRef":"u3L8NDluU+CiG52/PVsOwQ==","lnglat":{"type":"Point","coordinates":[-125.08109,49.6225]}},"createdBy":"M22iU8lNXFqdd6EWB6Eudw==","_change":{"user":"M22iU8lNXFqdd6EWB6Eudw==","historyId":"64142108f0cf008329602e7a","operation":"updateClimb","seq":0},"updatedAt":"2023-03-17T08:12:56.550Z"},{"_id":"3AJfA0/KSZKaTjlHTpI5MQ==","name":"Pew, Pew, Pew...","grades":{"yds":"5.9"},"type":{"trad":false,"sport":true,"bouldering":false,"alpine":false,"snow":false,"ice":false,"mixed":false,"aid":false,"tr":false},"gradeContext":"US","fa":"A. Klop","length":8,"content":{"description":"\nThe main trail to the wall leads you to the base of \"Pew, pew, pew...\". Climb past three bolts into this small dihedral system with a small tree. Crimpy and pumpy.\n\n\n\nBase of main wall\n\n8 bolts"},"metadata":{"left_right_index":-1,"areaRef":"u3L8NDluU+CiG52/PVsOwQ==","lnglat":{"type":"Point","coordinates":[-125.08109,49.6225]}},"createdBy":"M22iU8lNXFqdd6EWB6Eudw==","_change":{"user":"M22iU8lNXFqdd6EWB6Eudw==","historyId":"64142109f0cf008329602e84","operation":"updateClimb","seq":0},"updatedAt":"2023-03-17T08:12:57.023Z"}],"children":[],"ancestors":"2996145f-e1ba-5b56-9da8-30c64ccc3776,853ee9cb-d5b0-5376-8a2a-1958675243b4,e7eb252c-5158-5629-9b63-6baf3ba04e68,f29f29f7-86d2-55fb-be46-2e50ab575eb0,4dfc234d-da0a-5c67-9b82-216b1659b2e0,7809d062-b8af-59cb-999c-0dbc11ffc7cd,bb72fc34-396e-53e0-a21b-9dbf3d5b0ec1","pathTokens":["Canada","British Columbia","Vancouver Island","Comox Lake","Comox Lake","Upper Deck","Upper Deck"],"gradeContext":"US","aggregate":{"byGrade":[{"count":2,"label":"5.8"},{"count":2,"label":"5.9"}],"byDiscipline":{"trad":{"total":1,"bands":{"unknown":0,"beginner":1,"intermediate":0,"advanced":0,"expert":0}},"sport":{"total":3,"bands":{"unknown":0,"beginner":1,"intermediate":2,"advanced":0,"expert":0}}},"byGradeBand":{"unknown":0,"beginner":2,"intermediate":2,"advanced":0,"expert":0}},"metadata":{"isDestination":false,"leaf":true,"isBoulder":false,"lnglat":{"type":"Point","coordinates":[-125.08109,49.6225]},"bbox":[-125.0817841119903,49.622050339818145,-125.08039588800975,49.62294966018187],"left_right_index":-1,"ext_id":"","area_id":"u3L8NDluU+CiG52/PVsOwQ==","polygon":{"type":"Polygon","coordinates":[[[-125.0817841119903,49.622050339818145],[-125.08039588800975,49.622050339818145],[-125.08039588800975,49.62294966018187],[-125.0817841119903,49.62294966018187],[-125.0817841119903,49.622050339818145]]]}},"content":{"description":"Morning and late afternoon sun. Great view."},"density":0,"totalClimbs":0,"_change":{"user":"rxDUVMc5QUiq75Hpq+nDVw==","historyId":"64142109f0cf008329602e84","prevHistoryId":"64142108f0cf008329602e7a","operation":"updateClimb","seq":0},"createdBy":"rxDUVMc5QUiq75Hpq+nDVw==","__v":5,"createdAt":"2023-03-17T08:12:53.032Z","updatedAt":"2024-01-20T01:10:06.807Z","updatedBy":"M22iU8lNXFqdd6EWB6Eudw=="}