{"_id":"63689d5ce80bff5a994f47a9","area_name":"Kirkwood Lake","shortCode":"","climbs":[{"_id":"9Nei6VQoUletYp5Lli6PmA==","name":"Dabbers Roof","yds":"V5","grades":{"yds":"V5","font":"6C","vscale":"V5"},"fa":"unknown","type":{"bouldering":true},"safety":"UNSPECIFIED","metadata":{"lnglat":{"type":"Point","coordinates":[-120.0853,38.70624]},"left_right_index":999999,"mp_id":"119658148","mp_crag_id":"119634170","climb_id":"9Nei6VQoUletYp5Lli6PmA==","areaRef":"0zwb/1guWU2HDn2oVH+cfQ=="},"content":{"description":"Super fun gym-style moves!","protection":"","location":"Across the street from the trail to Ashy to Classy, down in the gully, look for chalked up roof."},"__v":0},{"_id":"+28T3p1pWGKhDUzVnvBrqA==","name":"Ashy to Classy","yds":"V8-9","grades":{"yds":"V8-9","font":"7B+","vscale":"V8-9"},"fa":"unknown","type":{"bouldering":true},"safety":"UNSPECIFIED","metadata":{"lnglat":{"type":"Point","coordinates":[-120.0853,38.70624]},"left_right_index":999999,"mp_id":"119634223","mp_crag_id":"119634170","climb_id":"+28T3p1pWGKhDUzVnvBrqA==","areaRef":"0zwb/1guWU2HDn2oVH+cfQ=="},"content":{"description":"Sit start on the left side of the boulder then move up to a big sloper before trending right towards the top. The stand is V7, not to be missed!","protection":"","location":"In a grotto, just east of \"Long Distance Runner\""},"__v":0}],"children":[],"ancestors":"1db1e8ba-a40e-587c-88a4-64f5ea814b8e,1e18b6dd-d8b1-5c36-b555-175190184622,6d6152bc-0bbc-501a-9891-f11b5d49c911,b9f8ec09-9fa9-5afe-8b68-a68ecda3e0ea,d33c1bff-582e-594d-870e-7da8547f9c7d","pathTokens":["USA","California","Lake Tahoe","Carson Pass Highway (88)","Kirkwood Lake"],"gradeContext":"US","aggregate":{"byGrade":[{"count":1,"label":"V5"},{"count":1,"label":"V8-9"}],"byDiscipline":{"bouldering":{"total":2,"bands":{"unknown":0,"beginner":0,"intermediate":0,"advanced":1,"expert":1}}},"byGradeBand":{"unknown":0,"beginner":0,"intermediate":0,"advanced":1,"expert":1}},"metadata":{"isBoulder":false,"isDestination":false,"leaf":true,"lnglat":{"type":"Point","coordinates":[-120.0853,38.70624]},"bbox":[-120.08587621975971,38.70579033981814,-120.08472378024031,38.706689660181866],"left_right_index":-1,"ext_id":"119634170","area_id":"0zwb/1guWU2HDn2oVH+cfQ==","polygon":{"type":"Polygon","coordinates":[[[-120.08587621975971,38.70579033981814],[-120.08472378024031,38.70579033981814],[-120.08472378024031,38.706689660181866],[-120.08587621975971,38.706689660181866],[-120.08587621975971,38.70579033981814]]]}},"content":{"description":""},"density":0,"totalClimbs":2,"__v":1,"createdAt":"2022-11-07T05:54:08.064Z","updatedAt":"2024-02-19T18:29:07.866Z"}